{"tau": 0.95, "alpha": 0.99, "eps": 1e-05, "vis_interval": 100, "recurrent_policy": false, "folder": "./results", "save_interval": 100, "log_dir": "./results_temp/", "actor_lambda": 0.01, "vis": true, "save_dir": "./trained_models/", "num_frames": 10000000.0, "seed": 5, "num_stack": 4, "algo": "trust_a2c", "num_processes": 16, "no_cuda": false, "use_gae": false, "target_update_interval": 10, "value_loss_coef": 0.5, "gamma": 0.99, "entropy_coef": 0.01, "num_steps": 5, "ppo_epoch": 4, "max_grad_norm": 0.5, "port": 8097, "lr": 0.0007, "target_tau": 0.001, "num_mini_batch": 32, "log_interval": 10, "env_name": "Walker2d-v1", "cuda": false, "no_vis": false, "clip_param": 0.2}